petutils/__init__.py
petutils/petutils.py
petutils-0.1.0.dist-info/METADATA
petutils-0.1.0.dist-info/WHEEL
petutils-0.1.0.dist-info/RECORD
